<?xml version="1.0" encoding="UTF-8"?>
<!DOCTYPE beans PUBLIC "-//SPRING//DTD BEAN//EN" "http://www.springframework.org/dtd/spring-beans.dtd">

<beans>

	<!--
			login controller
	-->
	<bean id="loginController" name="/login.htm" 
		class="org.helianto.core.web.LoginController">
	</bean>
	<!--
			flow controller
	-->
	<!--bean id="accessFlowController" name="/access.htm" 
		class="org.springframework.webflow.manager.mvc.FlowController">
		<property name="flow" ref="accessFlow"/>
	</bean-->
	<!--
			access flow
	-->
	<!--bean id="accessFlow" 
		class="org.springframework.webflow.config.XmlFlowFactoryBean">
		<property name="location" 
			value="classpath:flows/access-flow.xml"/>
	</bean-->
	<!--
			access action
	-->
	<bean id="accessAction" 
		class="org.helianto.core.webflow.access.AccessActionImpl">
		<property name="coreMgr" ref="coreMgr"/>
	</bean>
	<!--
			user flow
	-->
	<!--bean id="userFlow" 
		class="org.springframework.webflow.config.XmlFlowFactoryBean">
		<property name="location" 
			value="classpath:user-flow.xml"/>
	</bean-->

</beans>
